yourmum/__init__.py
yourmum-0.1.dist-info/DESCRIPTION.rst
yourmum-0.1.dist-info/METADATA
yourmum-0.1.dist-info/RECORD
yourmum-0.1.dist-info/WHEEL
yourmum-0.1.dist-info/metadata.json
yourmum-0.1.dist-info/top_level.txt
