Metadata-Version: 2.0
Name: yourmum
Version: 0.1
Summary: Probably the funniest your mum jokes! Customize jokes to use 'mum', 'mom', 'momma' or any other qualifier.
Home-page: https://github.com/bottines/yourmum.git
Author: Stéphane Bottine
Author-email: stephane.bottine@gmail.com
License: UNKNOWN
Platform: UNKNOWN
